<resources>
    <string name="lock">Zamykací obrazovka</string>
    <string name="sync">Sync</string>
    <string name="caffeina">Kofein</string>
    <string name="caffeina_stop">Klikněte na Kofein pro zastavení služby</string>
    <string name="caffeina_run">Kofein je spuštěn</string>
    <string name="brightness_auto">Automatický jas</string>
    <string name="sound">Hlasitost</string>
    <string name="select_app">Vyberte aplikaci</string>
    <string name="app">Aplikace &amp; zkratky</string>
    <string name="mono">In-Ear Audio</string>
    <string name="mono_run">In-Ear Audio je spuštěno</string>
    <string name="mono_stop">Klikněte na In-Ear Audio pro zastavení služby</string>
    <string name="reboot_simple">Restartovat</string>
    <string name="reboot_soft">Horký restart</string>
    <string name="reboot_recovery">Restart do recovery</string>
    <string name="reboot_bootloader">Restart do bootloaderu</string>
    <string name="reboot_shutdown">Vypnout</string>
    <string name="root_unavaible">Vaše zařízení není pravděpodobně rootováno…</string>
    <string name="reboot">Restartovat</string>
    <string name="ok">OK</string>
    <string name="screenshot">Screenshot</string>
    <string name="gps_only">GPS</string>
    <string name="gps_wifi">Síť</string>
    <string name="gps_all">GPS + síť</string>
    <string name="gps_off">Vypnuto</string>
    <string name="position">Pozice</string>
    <string name="share_screenshot">Sdílet screenshot s…</string>
    <string name="nfc">NFC</string>
    <string name="wait">Prosím počkejte</string>
    <string name="status">Skrýt notifikační lištu</string>
    <string name="nav">Skrýt navigační lištu</string>
    <string name="full">Skrýt všechny systémové lišty</string>
    <string name="none">Zobrazit všechny systémové lišty</string>
    <string name="immersive">Imersivní mód</string>
    <string name="reminder_public_text">Připomínka je spuštěna</string>
    <string name="dismiss">Smazat vše</string>
    <string name="reminder_empty_note">Přidejte nový text stisknutím tlačítka</string>
    <string name="reminder">Chytré upozornění</string>
    <string name="reply_label">Napiště text…</string>
    <string name="add_new_note_reminder">Přidat nový řádek</string>
    <string name="reminder_copy">Zkopírovat text</string>
    <string name="copied">Zkopírováno</string>
    <string name="delete_last">Smazat poslední řádek</string>
    <string name="hide_from_launcher">Skrýt z launcheru</string>
    <string name="sure">Jste si jistý/á??</string>
    <string name="cancel">Zrušit</string>
    <string name="reboot_to_refresh">Možná budete muset restartovat zařízení</string>
    <string name="volume_up">Hlasitost +</string>
    <string name="volume_down">Hlasitost -</string>
    <string name="store_screenshots">Uložit screenshoty místo sdílení</string>
    <string name="screenshot_done">Screenshot uložen</string>
    <string name="screenshot_touch_to_show">Klikněte pro zobrazení screenshotu</string>
    <string name="delete">Smazat</string>
    <string name="share">Sdílet</string>
    <string name="ringer">Hlasitost vyzvánění</string>
    <string name="permission_required">Vyžadováno povolení</string>
    <string name="in_ear_summary">Poslouchejte hudbu reproduktorem pro hovory. Užitečné pokud nemáte sluchátka</string>
    <string name="root_required">Vyžádováno povolení root</string>
    <string name="caffeina_summary">Udržuje obrazovku zapnutou</string>
    <string name="app_summary">Vyberte aplikaci pro spuštění</string>
    <string name="immersive_summary">Skryje systémové lišty</string>
    <string name="reminder_summary">Použijte upozornění pro zapsání čehokoliv</string>
    <string name="screenshot_summary">Udělejte screenshot jediným kliknutím</string>
    <string name="ringer_summary">Zvonění - Vibrace - Ztišit</string>
    <string name="contact">Kontakt</string>
    <string name="contact_summary">Rychle otevřete kontakt</string>
    <string name="sound_summary">Otevřete panel hlasitosti</string>
    <string name="brightness_auto_summary">Zapne nebo vypne automatický jas</string>
    <string name="thanks">Děkuji</string>
    <string name="calculator">Kalkulačka</string>
    <string name="calc_summary">Spustit systémovou kalkulačku</string>
    <string name="calc_not_found">Systémová kalkulačka nenalezena</string>
    <string name="sync_summary">Zapne nebo vypne synchronizaci</string>
    <string name="nfc_summary">Zapne nebo vypne NFC</string>
    <string name="in_ear_max">Hlasitost na maximum při aktivaci</string>
    <string name="heads_up">Heads-Up</string>
    <string name="screen_timeout">Čas vypnutí obrazovky</string>
    <string name="timer">Časovač</string>
    <string name="heads_up_summary">Zapne nebo vypne Heads Up upozornění</string>
    <string name="screen_timeout_summary">Nastavit čas vypnutí obrazovky</string>
    <string name="storage">Úložiště</string>
    <string name="storage_summary">Otevře systémový správce souborů</string>
    <string name="tally_counter">Počítadlo</string>
    <string name="tally_counter_summary">Rychlé počítadlo</string>
    <string name="timer_summary">Nastavit nový časovač</string>
    <string name="alarm">Budík</string>
    <string name="alarm_summary">Nastavit nový budík</string>
    <string name="bluefilter">Noční filtr obrazovky</string>
    <string name="bluefilter_color">Vyberte barvu filtru</string>
    <string name="bluefilter_summary">Aplikujte barevný filtr na obrazovku</string>
    <string name="brightness">Jas</string>
    <string name="brightness_summary">Upravit jas</string>
    <string name="leave_review">Zanechte recenzi</string>
    <string name="dice">Kostka</string>
    <string name="dice_summary">Hoďte kostkou</string>
    <string name="night_filter_working">Noční filtr je spuštěn</string>
    <string name="not_supported">Není podporováno</string>
    <string name="donation_s">$0.99</string>
    <string name="donation_s_effective">Obdržím asi $0.69</string>
    <string name="donation_m">$1.49</string>
    <string name="donation_m_effective">Obdržím asi $1.00</string>
    <string name="donation_l">$1.99</string>
    <string name="donation_l_effective">Obdržím asi $1.39</string>
    <string name="donation_xl">$4.49</string>
    <string name="donation_xl_effective">Obdržím asi $3.14</string>
    <string name="donate">Darovat</string>
    <string name="order_number">Číslo objednávky</string>
    <string name="search_tile">Hledat</string>
    <string name="search_summary">Hledat na internetu</string>
    <string name="search_tile_long_press">Spustit hlasové vyhledávání</string>
    <string name="storage_open_old_screen">Otevřít nastavení úložiště místo správce souborů</string>
    <string name="adb">ADB</string>
    <string name="play_pause">Přehrát / Pozastavit</string>
    <string name="play_pause_summary">Přehrát nebo pozastavit aktuální instanci přehrávače</string>
    <string name="never_show">Znovu nezobrazovat</string>
    <string name="in_ear_hide_screen">Skryjte obrazovku, když je telefon blízko vaší hlavy</string>
    <string name="data_mobile">Mobilní data</string>
    <string name="vpn">VPN</string>
    <string name="data_mobile_summary">Změňte stav mobilních dat</string>
    <string name="vpn_summary">Otevřít nastavení VPN</string>
    <string name="cast">Odeslat</string>
    <string name="cast_summary">Otevře obrazovku odeslání</string>
    <string name="help_translation">Pomoc s překladem</string>
    <string name="battery_saver">Šetřič baterie</string>
    <string name="not_supported_in_charging_state">Není k dispozici, když se telefon nabíjí</string>
    <string name="ambient_display">Ambientní displej</string>
    <string name="may_not_be_compatible">Nemusí být kompatibilní s vaším zařízením</string>
    <string name="adb_wifi">Adb přes LAN</string>
    <string name="command_to_execute">Proveďte tento příkaz na počítači pro připojení zařízení</string>
    <string name="invert_colors">Invertovat barvy</string>
    <string name="stop_at_screen_lock">Zastavte, když bude telefon zamknut</string>
    <string name="music_volume_tile">Hlasitost hudby</string>
    <string name="music_volume_tile_summary">Aktivujte nebo deaktivujte hlasitost hudby rychle</string>
    <string name="animations">Animace</string>
    <string name="animations_summary">Změňte měřítko animace</string>
    <string name="camera">Fotoaparát</string>
    <string name="camera_summary">Spusťte fotoaparát</string>
    <string name="camera_tile_record_video">Spustit fotoaparát ve video režimu</string>
    <string name="orientation">Otočení obrazovky</string>
    <string name="battery">Baterie</string>
    <string name="battery_level">Zobrazí úroveň baterie</string>
    <string name="battery_style">Styl baterie</string>
    <string name="notification_ongoing_channel">Probíhající služby</string>
    <string name="add">Přidat</string>
    <string name="remove">Odstranit</string>
    <string name="advise_edit_tiles_from_panel">%s this tile editing your quick settings panel.\nFor more information, click the Help button at the top of this page</string>
    <string name="vibrate_on_ring">Vibrovat při hovoru</string>
    <string name="use_letter_as_app_icon">Použijte první znak jako ikonu aplikace</string>
    <string name="accessibility_mono_audio">Mono zvuk</string>
    <string name="accessibility_mono_audio_summary">Je to ekvivalent Nastavení > Přístupnost > Použití mono zvuku</string>
    <string name="mobile_data_type">Typ mobilních dat</string>
    <string name="mobile_data_type_summary">Otevřít nastavení mobilních dat</string>
    <string name="monochrome">Mód čtení</string>
    <string name="monochrome_summary">Filtruje barvy obrazovky na černobílou</string>
    <string name="reboot_system_ui">Obnovit systémové uživatelské rozhraní</string>
    <string name="input_method_picker">Výběr metody zadávání</string>
    <string name="immersive_preference">Vyberte si svůj oblíbený imersivní režim</string>
    <string name="immersive_pref_generic">Zvolit pokaždé</string>
    <string name="free_space">Volné místo:</string>
    <string name="hotspot">Hotspot</string>
    <string name="request_admin_explanation">Tato aplikace používá oprávnění administrátora zařízení.\n
        Toto oprávnění je vyžadováno k uzamčení obrazovky, když uživatel klepne na \'Zamknout obrazovku\'. Toto oprávnění se nikdy nepoužije pro jiné účely</string>
    <string name="welcome_home_message">Vítejte v Quick Settings</string>
    <string name="home">Domů</string>
    <string name="categories">Kategorie</string>
    <string name="utilities">Nástroje</string>
    <string name="multimedia">Multimédia</string>
    <string name="shortcuts">Zkratky</string>
    <string name="system_no_root">System (no root)</string>
    <string name="system_secure_adb">System (secure)</string>
    <string name="system_root_only">System (root only)</string>
    <string name="for_developers">Toggles for developers</string>
    <string name="app_1">App &amp; Shortcuts #1</string>
    <string name="app_2">App &amp; Shortcuts #2</string>
    <string name="app_3">App &amp; Shortcuts #3</string>
    <string name="orientation_summary">Nastavit orientaci obrazovky manuálně (180° zahrnuto)</string>
    <string name="input_method_picker_summary">Rychle změnit metodu zadávání</string>
    <string name="hotspot_summary">Povolit hotspot WiFi</string>
    <string name="battery_saver_summary">Aktivujte nebo deaktivujte AOSP úsporu baterie</string>
    <string name="position_summary">Změňte režim polohy pomocí klepnutí</string>
    <string name="adb_summary">Aktivujte nebo deaktivujte službu ADB</string>
    <string name="adb_wifi_summary">Aktivujte nebo deaktivujte ADB přes WiFi</string>
    <string name="nothing_to_customize">Zde není nic, co byste si mohli přizpůsobit</string>
    <string name="privacy_policy">Zásady ochrany osobních údajů</string>
    <string name="licenses">Licence</string>
    <string name="search_result_title">Výsledky hledání pro "%s"</string>
    <string name="empty_search_results">Nic nenalezeno.</string>
    <string name="save">Uložit</string>
    <string name="search">Hledat</string>
    <string name="led_tile">LED notifikační dioda</string>
    <string name="led_tile_summary">Povolení nebo zakázání LED diody</string>
    <string name="change_theme">Změnit styl</string>
    <string name="dark_theme">Tmavý styl</string>
    <string name="light_theme">Světlý styl</string>
</resources>
